pylingo/__init__.py
py_lingo-0.0.1b1.dist-info/LICENSE
py_lingo-0.0.1b1.dist-info/METADATA
py_lingo-0.0.1b1.dist-info/WHEEL
py_lingo-0.0.1b1.dist-info/top_level.txt
py_lingo-0.0.1b1.dist-info/RECORD
