Metadata-Version: 2.1
Name: py-lingo
Version: 0.0.1b1
Summary: Utilities for saving Scikit-Learn Linear Models in HDF5 format.
Home-page: https://github.com/markdouthwaite/py-lingo
Author: Mark Douthwaite
Author-email: mark@douthwaite.io
License: MIT
Platform: UNKNOWN
Classifier: Intended Audience :: Developers
Classifier: Intended Audience :: Science/Research
Classifier: License :: OSI Approved :: MIT License
Classifier: Programming Language :: Python :: 3
Classifier: Programming Language :: Python :: 3.6
Classifier: Programming Language :: Python :: 3.7
Classifier: Topic :: Software Development :: Libraries
Classifier: Topic :: Software Development :: Libraries :: Python Modules
Requires-Dist: numpy (==1.19.2)
Requires-Dist: h5py (==2.10.0)
Requires-Dist: scikit-learn (==0.23.2)
Provides-Extra: tests
Requires-Dist: pytest ; extra == 'tests'
Requires-Dist: black ; extra == 'tests'
Requires-Dist: isort ; extra == 'tests'
Requires-Dist: wheel ; extra == 'tests'
Requires-Dist: setuptools ; extra == 'tests'
